<odoo>
    <data>
        <record id="reetiquetado" model="stock.required_process">
            <field name="name">Reetiquetado</field>
        </record>

        <record id="reestibado" model="stock.required_process">
            <field name="name">Reestibado</field>
        </record>

        <record id="vinipelado" model="stock.required_process">
            <field name="name">Vinipelado</field>
        </record>

        <record id="zunchado" model="stock.required_process">
            <field name="name">Zunchado</field>
        </record>
        
    </data>
</odoo>